readpe
