Metadata-Version: 2.1
Name: readpe
Version: 0.2
Summary: A cross platform tool to work with PE files from the command line.
Home-page: https://github.com/N1ght-W0lf/readpe
Author: Abdallah Elshinbary
Author-email: abdallahelshinbary82@gmail.com
License: MIT
Platform: UNKNOWN
Classifier: Environment :: Console
Classifier: License :: OSI Approved :: MIT License
Classifier: Programming Language :: Python :: 2
Classifier: Programming Language :: Python :: 3
Classifier: Operating System :: OS Independent
